my_own_package/__init__.py
Bogdan_first_own_package-0.2.0.dist-info/METADATA
Bogdan_first_own_package-0.2.0.dist-info/WHEEL
Bogdan_first_own_package-0.2.0.dist-info/top_level.txt
Bogdan_first_own_package-0.2.0.dist-info/RECORD
