Metadata-Version: 2.1
Name: Bogdan-first-own-package
Version: 0.2.0
Summary: This is my frist package
Author: Bogdan-BF
Author-email: b0gdan4x@yahoo.com
